musiccast2mqtt/__init__.py
musiccast2mqtt/musiccast2mqtt.conf
musiccast2mqtt/musiccast2mqtt_OER.conf
musiccast2mqtt/musiccast_checks.py
musiccast2mqtt/musiccast_comm.py
musiccast2mqtt/musiccast_data.py
musiccast2mqtt/musiccast_device.py
musiccast2mqtt/musiccast_exceptions.py
musiccast2mqtt/musiccast_input.py
musiccast2mqtt/musiccast_interface.py
musiccast2mqtt/musiccast_map.json
musiccast2mqtt/musiccast_map_OER.json
musiccast2mqtt/musiccast_start.py
musiccast2mqtt/musiccast_sysdef.json
musiccast2mqtt/musiccast_sysdef_OER.json
musiccast2mqtt/musiccast_sysdef_schema.json
musiccast2mqtt/musiccast_sysdef_template_json.py
musiccast2mqtt/musiccast_system.py
musiccast2mqtt/musiccast_zone.py
musiccast2mqtt/version.py
musiccast2mqtt-0.114.dist-info/METADATA
musiccast2mqtt-0.114.dist-info/RECORD
musiccast2mqtt-0.114.dist-info/WHEEL
musiccast2mqtt-0.114.dist-info/entry_points.txt
musiccast2mqtt-0.114.dist-info/top_level.txt
